README.md
supreme_task/__init__.py
supreme_task/py.typed
supreme_task/tasks.py
supreme_task-0.1.1.dist-info/METADATA
supreme_task-0.1.1.dist-info/WHEEL
supreme_task-0.1.1.dist-info/RECORD
