Metadata-Version: 2.1
Name: supreme-task
Version: 0.1.1
Summary: Prefect tasks plus added functionality to enforce type checking and help in debugging helping to reduce negative engineering!
Home-page: https://github.com/marwan116/supreme-task/
Keywords: prefect,tasks,workflow,orchestration
Requires-Python: >=3.8,<3.11
Classifier: Programming Language :: Python :: 3
Classifier: Programming Language :: Python :: 3.8
Classifier: Programming Language :: Python :: 3.9
Classifier: Programming Language :: Python :: 3.10
Requires-Dist: prefect (>=2.0.0,<3.0.0)
Requires-Dist: typeguard (>=4.0.0,<5.0.0)
Project-URL: Documentation, https://github.com/marwan116/supreme-task/
Project-URL: Repository, https://github.com/marwan116/supreme-task/
